QwantAI/__init__.py
QwantAI/core.py
QwantAI/websocket_handler.py
QwantAI-1.0.1.dist-info/METADATA
QwantAI-1.0.1.dist-info/WHEEL
QwantAI-1.0.1.dist-info/top_level.txt
QwantAI-1.0.1.dist-info/RECORD
