Metadata-Version: 2.1
Name: QwantAI
Version: 1.0.1
Summary: A Python library to interact with the Qwant search engine AI.
Home-page: https://github.com/Ramona-Flower/QwantAI
Author: Ramona
License: MIT
Classifier: Programming Language :: Python :: 3
Classifier: License :: OSI Approved :: MIT License
Classifier: Operating System :: OS Independent
Requires-Python: >=3.6
Requires-Dist: requests ==2.31.0
Requires-Dist: websocket-client ==1.6.0
